senitherweight/__init__.py
senitherweight/constants.py
senitherweight/main.py
senitherweight/utils.py
senitherweight/calcs/__init__.py
senitherweight/calcs/dungeon_weight.py
senitherweight/calcs/skill_weight.py
senitherweight/calcs/slayer_weight.py
senitherweight-0.0.1.dist-info/LICENSE
senitherweight-0.0.1.dist-info/METADATA
senitherweight-0.0.1.dist-info/WHEEL
senitherweight-0.0.1.dist-info/top_level.txt
senitherweight-0.0.1.dist-info/RECORD
