Metadata-Version: 2.1
Name: senitherweight
Version: 0.0.1
Summary: Hypixel SkyBlock Weight Calculator.
Home-page: UNKNOWN
Author: timnoot
Author-email: <hypixelskyhub@gmail.com>
License: UNKNOWN
Keywords: python,hypixel,skyblock,senither weight,weight,senither
Platform: UNKNOWN
Classifier: Development Status :: 5 - Production/Stable
Classifier: Intended Audience :: Developers
Classifier: Operating System :: OS Independent
Classifier: License :: OSI Approved :: MIT License
Classifier: Programming Language :: Python :: 3
Requires-Dist: aiohttp
